[
  {
    "english": "listen",
    "chinese": "聽"
  },
  {
    "english": "voice",
    "chinese": "聲音；歌喉"
  },
  {
    "english": "stand up",
    "chinese": "站起來"
  },
  {
    "english": "sit down",
    "chinese": "坐下"
  },
  {
    "english": "take a photo",
    "chinese": "拍照"
  },
  {
    "english": "make",
    "chinese": "製造"
  },
  {
    "english": "any",
    "chinese": "任何(的)"
  },
  {
    "english": "noise",
    "chinese": "噪音"
  },
  {
    "english": "can't",
    "chinese": "不能；不會"
  },
  {
    "english": "talk",
    "chinese": "講話"
  },
  {
    "english": "noisy",
    "chinese": "吵鬧的"
  },
  {
    "english": "late",
    "chinese": "晚的；遲到的"
  },
  {
    "english": "early",
    "chinese": "早的；初期的"
  },
  {
    "english": "sidewalk",
    "chinese": "人行道"
  },
  {
    "english": "song",
    "chinese": "歌曲"
  },
  {
    "english": "check out",
    "chinese": "查看"
  },
  {
    "english": "cross",
    "chinese": "跨越"
  },
  {
    "english": "road",
    "chinese": "道路"
  },
  {
    "english": "real",
    "chinese": "真的；真實的"
  },
  {
    "english": "all the time",
    "chinese": "一直"
  },
  {
    "english": "Guess what?",
    "chinese": "你猜怎麼著？"
  },
  {
    "english": "traffic lights",
    "chinese": "紅綠燈"
  },
  {
    "english": "ground",
    "chinese": "地面"
  },
  {
    "english": "design",
    "chinese": "設計"
  },
  {
    "english": "user",
    "chinese": "使用者"
  },
  {
    "english": "download",
    "chinese": "下載"
  },
  {
    "english": "warn",
    "chinese": "警告"
  },
  {
    "english": "oncoming",
    "chinese": "迎面而來的"
  },
  {
    "english": "crosswalk",
    "chinese": "斑馬線"
  },
  {
    "english": "also",
    "chinese": "也"
  },
  {
    "english": "the USA",
    "chinese": "美國"
  },
  {
    "english": "special",
    "chinese": "特別的"
  },
  {
    "english": "lane",
    "chinese": "小路；小巷"
  },
  {
    "english": "way",
    "chinese": "方式；方法；路"
  },
  {
    "english": "other",
    "chinese": "其他的"
  },
  {
    "english": "watch out",
    "chinese": "小心；注意"
  }
]